slurm_requests/__about__.py
slurm_requests/__init__.py
slurm_requests-2.1.0.dist-info/METADATA
slurm_requests-2.1.0.dist-info/WHEEL
slurm_requests-2.1.0.dist-info/licenses/LICENSE.txt
slurm_requests-2.1.0.dist-info/RECORD
