Metadata-Version: 2.4
Name: slurm-requests
Version: 2.1.0
Summary: Lightweight asynchronous SLURM REST requests with proxy support.
Project-URL: Documentation, https://github.com/Kwasniok/pypi-slurm-requests#readme
Project-URL: Issues, https://github.com/Kwasniok/pypi-slurm-requests/issues
Project-URL: Source, https://github.com/Kwasniok/pypi-slurm-requests
Author-email: Kwasniok <Kwasniok@users.noreply.github.com>
Maintainer-email: Kwasniok <Kwasniok@users.noreply.github.com>
License-Expression: CC-BY-SA-4.0
License-File: LICENSE.txt
Keywords: rest,slurm
Classifier: Development Status :: 4 - Beta
Classifier: Programming Language :: Python
Classifier: Programming Language :: Python :: 3.10
Classifier: Programming Language :: Python :: 3.11
Classifier: Programming Language :: Python :: 3.12
Classifier: Programming Language :: Python :: 3.13
Classifier: Programming Language :: Python :: 3.14
Requires-Python: >=3.10
Requires-Dist: rest-requests>=2.1.0
